odoo/addons/mail_queue_job/README.rst
odoo/addons/mail_queue_job/__init__.py
odoo/addons/mail_queue_job/__manifest__.py
odoo/addons/mail_queue_job/hooks.py
odoo/addons/mail_queue_job/i18n/ca.po
odoo/addons/mail_queue_job/i18n/de.po
odoo/addons/mail_queue_job/i18n/es.po
odoo/addons/mail_queue_job/i18n/es_CO.po
odoo/addons/mail_queue_job/i18n/fi.po
odoo/addons/mail_queue_job/i18n/fr.po
odoo/addons/mail_queue_job/i18n/hr.po
odoo/addons/mail_queue_job/i18n/hu.po
odoo/addons/mail_queue_job/i18n/it.po
odoo/addons/mail_queue_job/i18n/lv.po
odoo/addons/mail_queue_job/i18n/mail_connector_queue.pot
odoo/addons/mail_queue_job/i18n/mail_queue_job.pot
odoo/addons/mail_queue_job/i18n/nb.po
odoo/addons/mail_queue_job/i18n/nl.po
odoo/addons/mail_queue_job/i18n/pt.po
odoo/addons/mail_queue_job/i18n/pt_BR.po
odoo/addons/mail_queue_job/i18n/sl.po
odoo/addons/mail_queue_job/i18n/sv.po
odoo/addons/mail_queue_job/i18n/th.po
odoo/addons/mail_queue_job/i18n/zh_CN.po
odoo/addons/mail_queue_job/models/__init__.py
odoo/addons/mail_queue_job/models/mail_mail.py
odoo/addons/mail_queue_job/readme/CONTRIBUTORS.rst
odoo/addons/mail_queue_job/readme/DESCRIPTION.rst
odoo/addons/mail_queue_job/readme/HISTORY.rst
odoo/addons/mail_queue_job/readme/USAGE.rst
odoo/addons/mail_queue_job/static/description/icon.png
odoo/addons/mail_queue_job/static/description/index.html
odoo/addons/mail_queue_job/tests/__init__.py
odoo/addons/mail_queue_job/tests/test_mail_mail.py
odoo/addons/mail_queue_job/views/mail_mail.xml
odoo11_addon_mail_queue_job-11.0.1.0.1.99.dev8.dist-info/METADATA
odoo11_addon_mail_queue_job-11.0.1.0.1.99.dev8.dist-info/WHEEL
odoo11_addon_mail_queue_job-11.0.1.0.1.99.dev8.dist-info/top_level.txt
odoo11_addon_mail_queue_job-11.0.1.0.1.99.dev8.dist-info/RECORD
